scorecard.py
scorecard-0.3.dist-info/entry_points.txt
scorecard-0.3.dist-info/WHEEL
scorecard-0.3.dist-info/METADATA
scorecard-0.3.dist-info/RECORD
