Metadata-Version: 1.2
Name: scorecard
Version: 0.3
Summary: PMML Scorecard generator
Home-page: https://github.com/ncoghlan/pyscorecard/
License: UNKNOWN
Author: Nick Coghlan
Author-email: ncoghlan@redhat.com
Classifier: License :: OSI Approved :: Apache Software License
Requires-Dist: lxml
Requires-Dist: tabulate
